network_diffusion/__init__.py
network_diffusion/logger.py
network_diffusion/metrics.py
network_diffusion/simulator.py
network_diffusion/utils.py
network_diffusion/mln/__init__.py
network_diffusion/mln/actor.py
network_diffusion/mln/cbim.py
network_diffusion/mln/centralities.py
network_diffusion/mln/centrality_discount.py
network_diffusion/mln/functions.py
network_diffusion/mln/kppshell.py
network_diffusion/mln/mlnetwork.py
network_diffusion/mln/mlnetwork_torch.py
network_diffusion/mln/mds/__init__.py
network_diffusion/mln/mds/greedy_search.py
network_diffusion/mln/mds/local_improvement.py
network_diffusion/mln/mds/utils.py
network_diffusion/models/__init__.py
network_diffusion/models/base_model.py
network_diffusion/models/dsaa_model.py
network_diffusion/models/mic_model.py
network_diffusion/models/mlt_model.py
network_diffusion/models/tne_model.py
network_diffusion/models/utils/__init__.py
network_diffusion/models/utils/compartmental.py
network_diffusion/models/utils/types.py
network_diffusion/nets/__init__.py
network_diffusion/nets/l2_course_net.py
network_diffusion/nets/mln_generator.py
network_diffusion/nets/toy_network_cim.py
network_diffusion/nets/toy_network_piotr.py
network_diffusion/nets/data/1_course_edges.csv
network_diffusion/nets/data/1_ego_edges.csv
network_diffusion/nets/data/1_nodes.csv
network_diffusion/nets/data/2_course_edges.csv
network_diffusion/nets/data/2_ego_edges.csv
network_diffusion/nets/data/2_nodes.csv
network_diffusion/nets/data/3_course_edges.csv
network_diffusion/nets/data/3_ego_edges.csv
network_diffusion/nets/data/3_nodes.csv
network_diffusion/seeding/__init__.py
network_diffusion/seeding/base_selector.py
network_diffusion/seeding/betweenness_selector.py
network_diffusion/seeding/cbim_selector.py
network_diffusion/seeding/cim.py
network_diffusion/seeding/closeness_selector.py
network_diffusion/seeding/degreecentrality_selector.py
network_diffusion/seeding/driveractor_selector.py
network_diffusion/seeding/katz_selector.py
network_diffusion-0.18.1.dist-info/LICENSE
network_diffusion-0.18.1.dist-info/METADATA
network_diffusion-0.18.1.dist-info/WHEEL
network_diffusion-0.18.1.dist-info/top_level.txt
network_diffusion-0.18.1.dist-info/RECORD
