Metadata-Version: 2.1
Name: network_diffusion
Version: 0.18.1
Summary: Network Diffusion - a package for simulating spreading phenomena.
Author-email: Michał Czuba <michal.czuba@pwr.edu.pl>, Piotr Bródka <piotr.brodka@pwr.edu.pl>
License: MIT License
Project-URL: Homepage, https://github.com/anty-filidor/network_diffusion
Project-URL: Documentation, https://network-diffusion.readthedocs.io/en/latest/
Project-URL: Issues, https://github.com/anty-filidor/network_diffusion/issues
Keywords: influence maximisation,influence maximization,multilayer networks,networkx,network science,phenomena spreading,simulation,social influence,social networks,spreading,temporal networks
Classifier: Development Status :: 4 - Beta
Classifier: Intended Audience :: Science/Research
Classifier: Topic :: Scientific/Engineering :: Artificial Intelligence
Classifier: Topic :: Scientific/Engineering :: Information Analysis
Classifier: License :: OSI Approved :: MIT License
Classifier: Programming Language :: Python :: 3.12
Requires-Python: >=3.12
License-File: LICENSE
Requires-Dist: bidict~=0.23.1
Requires-Dist: dynetx~=0.3.2
Requires-Dist: matplotlib~=3.9.0
Requires-Dist: networkx~=3.3
Requires-Dist: numpy~=2.0.0
Requires-Dist: pandas~=2.2.2
Requires-Dist: scipy~=1.13.1
Requires-Dist: torch~=2.3.1
Requires-Dist: tqdm~=4.66.4
Requires-Dist: uunet==2.2.0
